MANIFEST.in
README.rst
README.txt
dev_requirements.txt
requirements.txt
setup.py
test_requirements.txt
version.txt
cloudshell/__init__.py
cloudshell/devices/__init__.py
cloudshell/devices/cli_handler_impl.py
cloudshell/devices/cli_handler_interface.py
cloudshell/devices/driver_helper.py
cloudshell/devices/json_request_helper.py
cloudshell/devices/networking_utils.py
cloudshell/devices/snmp_handler.py
cloudshell/devices/snmp_handler_interface.py
cloudshell/devices/autoload/__init__.py
cloudshell/devices/autoload/autoload_builder.py
cloudshell/devices/autoload/autoload_migration_helper.py
cloudshell/devices/autoload/device_names.py
cloudshell/devices/flows/__init__.py
cloudshell/devices/flows/action_flows.py
cloudshell/devices/flows/cli_action_flows.py
cloudshell/devices/flows/snmp_action_flows.py
cloudshell/devices/runners/__init__.py
cloudshell/devices/runners/autoload_runner.py
cloudshell/devices/runners/configuration_runner.py
cloudshell/devices/runners/connectivity_runner.py
cloudshell/devices/runners/firmware_runner.py
cloudshell/devices/runners/run_command_runner.py
cloudshell/devices/runners/state_runner.py
cloudshell/devices/runners/interfaces/__init__.py
cloudshell/devices/runners/interfaces/autoload_runner_interface.py
cloudshell/devices/runners/interfaces/configuration_runner_interface.py
cloudshell/devices/runners/interfaces/connectivity_runner_interface.py
cloudshell/devices/runners/interfaces/firmware_runner_interface.py
cloudshell/devices/runners/interfaces/run_command_runner_interface.py
cloudshell/devices/runners/interfaces/state_runner_interface.py
cloudshell/devices/standards/__init__.py
cloudshell/devices/standards/base.py
cloudshell/devices/standards/validators.py
cloudshell/devices/standards/firewall/__init__.py
cloudshell/devices/standards/firewall/autoload_structure.py
cloudshell/devices/standards/firewall/configuration_attributes_structure.py
cloudshell/devices/standards/load_balancing/__init__.py
cloudshell_networking_devices.egg-info/PKG-INFO
cloudshell_networking_devices.egg-info/SOURCES.txt
cloudshell_networking_devices.egg-info/dependency_links.txt
cloudshell_networking_devices.egg-info/requires.txt
cloudshell_networking_devices.egg-info/top_level.txt
