Metadata-Version: 1.0
Name: cloudshell-networking-devices
Version: 2.8.0
Summary: QualiSystems Python package
Home-page: https://github.com/QualiSystems/cloudshell-networking-devices
Author: QualiSystems
Author-email: info@qualisystems.com
License: UNKNOWN
Platform: UNKNOWN
